endi_celery/__init__.py
endi_celery/accounting.py
endi_celery/conf.py
endi_celery/exception.py
endi_celery/hacks.py
endi_celery/interfaces.py
endi_celery/locks.py
endi_celery/mail.py
endi_celery/models.py
endi_celery/transactional_task.py
endi_celery/parsers/__init__.py
endi_celery/parsers/cegid.py
endi_celery/parsers/ebp.py
endi_celery/parsers/isacompta.py
endi_celery/parsers/quadra.py
endi_celery/parsers/sage.py
endi_celery/parsers/sage_generation_expert.py
endi_celery/schedulers/__init__.py
endi_celery/schedulers/tasks.py
endi_celery/tasks/__init__.py
endi_celery/tasks/accounting_measure_compute.py
endi_celery/tasks/accounting_parser.py
endi_celery/tasks/csv_import.py
endi_celery/tasks/export.py
endi_celery/tasks/json_import.py
endi_celery/tasks/mail.py
endi_celery/tasks/notification.py
endi_celery/tasks/tasks.py
endi_celery/tasks/utils.py
endi_celery-6.7.8.dist-info/LICENSE.txt
endi_celery-6.7.8.dist-info/METADATA
endi_celery-6.7.8.dist-info/WHEEL
endi_celery-6.7.8.dist-info/entry_points.txt
endi_celery-6.7.8.dist-info/top_level.txt
endi_celery-6.7.8.dist-info/RECORD
