Metadata-Version: 2.1
Name: endi-celery
Version: 6.7.8
Summary: endi_celery
Home-page: https://framagit.org/endi/endi_celery
Author: Coopérer Pour Entreprendre
Author-email: contact@endi.coop
License: GPLv3
Keywords: web wsgi bfg pylons pyramid celery
Classifier: License :: OSI Approved :: GNU General Public License v3 (GPLv3)
Classifier: Programming Language :: Python
Classifier: Framework :: Pyramid
Classifier: Topic :: Internet :: WWW/HTTP
Classifier: Topic :: Internet :: WWW/HTTP :: WSGI :: Application
License-File: LICENSE.txt
Requires-Dist: celery (==4.4.7)
Requires-Dist: pyramid-celery (==4.0.0)
Requires-Dist: redis (==3.5.3)
Requires-Dist: kombu (==4.6.11)
Requires-Dist: sylk-parser (==0.5)
